AUTHORS
LICENSE
MANIFEST.in
README
README.rst
setup.py
django_smileys_plus.egg-info/PKG-INFO
django_smileys_plus.egg-info/SOURCES.txt
django_smileys_plus.egg-info/dependency_links.txt
django_smileys_plus.egg-info/not-zip-safe
django_smileys_plus.egg-info/requires.txt
django_smileys_plus.egg-info/top_level.txt
smileys/__init__.py
smileys/admin.py
smileys/models.py
smileys/templatetags/__init__.py
smileys/templatetags/smiley_tags.py