Metadata-Version: 1.1
Name: django-smileys-plus
Version: 0.2.0-beta
Summary: Easily add, use and manage smileys on your Django-powered site.
Home-page: http://bitbucket.org/artscoop/django-smileys/
Author: Artscoop
Author-email: artscoop93@gmail.com
License: BSD
Keywords: django,image,smiley,useless,fun
Platform: UNKNOWN
Classifier: Development Status :: 4 - Beta
Classifier: Environment :: Web Environment
Classifier: Framework :: Django
Classifier: Intended Audience :: Developers
Classifier: Intended Audience :: End Users/Desktop
Classifier: License :: OSI Approved :: BSD License
Classifier: Natural Language :: English
Classifier: Operating System :: OS Independent
Classifier: Programming Language :: Python
Classifier: Topic :: Artistic Software
Classifier: Topic :: Internet :: WWW/HTTP :: Dynamic Content
Classifier: Topic :: Multimedia :: Graphics
